[
  {
    "universityName": "Harvard University",
    "universityImage": "https://i.ibb.co.com/n3g8jC4/Harvard-University-shield.png",
    "scholarshipCategory": "Merit-Based",
    "universityLocation": { "country": "USA", "city": "Cambridge" },
    "applicationDeadline": "2025-02-15",
    "subjectName": "Engineering",
    "scholarshipDescription": "This scholarship is for outstanding undergraduate students in engineering.",
    "stipend": "20000 annually",
    "postDate": "2025-01-01",
    "serviceCharge": "100",
    "applicationFees": "50"
  },
  {
    "universityName": "Oxford University",
    "universityImage": "https://i.ibb.co.com/VWpH13B/Uni-Oxford-logo-svg.png",
    "scholarshipCategory": "Research",
    "universityLocation": { "country": "UK", "city": "Oxford" },
    "applicationDeadline": "2025-03-01",
    "subjectName": "Medicine",
    "scholarshipDescription": "A research grant for postgraduate students in the field of medicine.",
    "stipend": "15000 annually",
    "postDate": "2025-01-05",
    "serviceCharge": "120",
    "applicationFees": "60"
  },
  {
    "universityName": "Stanford University",
    "universityImage": "https://i.ibb.co.com/BN2kmzg/Seal-of-Leland-Stanford-Junior-University-svg.png",
    "scholarshipCategory": "Community-Based",
    "universityLocation": { "country": "USA", "city": "Stanford" },
    "applicationDeadline": "2025-04-10",
    "subjectName": "Computer Science",
    "scholarshipDescription": "Aimed at students contributing to their communities through technology.",
    "stipend": null,
    "postDate": "2025-01-12",
    "serviceCharge": "50",
    "applicationFees": "20"
  },
  {
    "universityName": "University of Toronto",
    "universityImage": "https://i.ibb.co.com/0ZqtkV5/Utoronto-coa-svg.png",
    "scholarshipCategory": "Need-Based",
    "universityLocation": { "country": "Canada", "city": "Toronto" },
    "applicationDeadline": "2025-05-15",
    "subjectName": "Business Administration",
    "scholarshipDescription": "Designed for students demonstrating financial need.",
    "stipend": "10000 annually",
    "postDate": "2025-01-18",
    "serviceCharge": "80",
    "applicationFees": "40"
  },
  {
    "universityName": "Australian National University",
    "universityImage": "https://i.ibb.co.com/WWjJd8n/Australian-National-University-coat-of-arms-svg.png",
    "scholarshipCategory": "International",
    "universityLocation": { "country": "Australia", "city": "Canberra" },
    "applicationDeadline": "2025-06-01",
    "subjectName": "Environmental Science",
    "scholarshipDescription": "For international students pursuing Environmental Science.",
    "stipend": "12000 annually",
    "postDate": "2025-01-20",
    "serviceCharge": "90",
    "applicationFees": "30"
  },
  {
    "universityName": "University of Tokyo",
    "universityImage": "https://i.ibb.co.com/Bcn4MbW/University-of-Tokyo-mark-svg.png",
    "scholarshipCategory": "Academic Excellence",
    "universityLocation": { "country": "Japan", "city": "Tokyo" },
    "applicationDeadline": "2025-03-20",
    "subjectName": "Physics",
    "scholarshipDescription": "A scholarship for students excelling academically in Physics.",
    "stipend": "18000 annually",
    "postDate": "2025-01-22",
    "serviceCharge": "110",
    "applicationFees": "70"
  },
  {
    "universityName": "National University of Singapore",
    "universityImage": "https://i.ibb.co.com/VJWxTHX/NUS-coat-of-arms-svg.png",
    "scholarshipCategory": "Leadership",
    "universityLocation": { "country": "Singapore", "city": "Singapore" },
    "applicationDeadline": "2025-05-30",
    "subjectName": "Economics",
    "scholarshipDescription": "Targeted at students with exceptional leadership qualities.",
    "stipend": "22000 annually",
    "postDate": "2025-01-25",
    "serviceCharge": "100",
    "applicationFees": "80"
  },
  {
    "universityName": "University of Zurich",
    "universityImage": "https://i.ibb.co.com/tcTQnLm/Uni-Zuerich-Siegel-svg.png",
    "scholarshipCategory": "STEM",
    "universityLocation": { "country": "Switzerland", "city": "Zurich" },
    "applicationDeadline": "2025-06-15",
    "subjectName": "Mechanical Engineering",
    "scholarshipDescription": "Scholarship for excellence in STEM fields.",
    "stipend": null,
    "postDate": "2025-01-28",
    "serviceCharge": "150",
    "applicationFees": "90"
  },
  {
    "universityName": "University of Cape Town",
    "universityImage": "https://i.ibb.co.com/tc9ZMWS/University-of-Cape-Town-logo-svg.png",
    "scholarshipCategory": "Humanitarian",
    "universityLocation": { "country": "South Africa", "city": "Cape Town" },
    "applicationDeadline": "2025-07-01",
    "subjectName": "Political Science",
    "scholarshipDescription": "Supports students committed to humanitarian work.",
    "stipend": "8000 annually",
    "postDate": "2025-01-30",
    "serviceCharge": "70",
    "applicationFees": "25"
  },
  {
    "universityName": "University of Melbourne",
    "universityImage": "https://i.ibb.co.com/4st7535/University-of-Melbourne-svg.png",
    "scholarshipCategory": "Arts",
    "universityLocation": { "country": "Australia", "city": "Melbourne" },
    "applicationDeadline": "2025-08-01",
    "subjectName": "Performing Arts",
    "scholarshipDescription": "For talented students in the performing arts.",
    "stipend": "5000 annually",
    "postDate": "2025-02-02",
    "serviceCharge": "85",
    "applicationFees": "35"
  },
  {
    "universityName": "Massachusetts Institute of Technology (MIT)",
    "universityImage": "https://i.ibb.co.com/YhJbBc3/MIT-Seal-svg.png",
    "scholarshipCategory": "Technology Innovation",
    "universityLocation": { "country": "USA", "city": "Cambridge" },
    "applicationDeadline": "2025-02-25",
    "subjectName": "Artificial Intelligence",
    "scholarshipDescription": "For students innovating in AI and technology.",
    "stipend": "25000 annually",
    "postDate": "2025-02-01",
    "serviceCharge": "150",
    "applicationFees": "75"
  },
  {
    "universityName": "Princeton University",
    "universityImage": "https://i.ibb.co.com/JdnpQTP/Princeton-seal-svg.png",
    "scholarshipCategory": "Undergraduate",
    "universityLocation": { "country": "USA", "city": "Princeton" },
    "applicationDeadline": "2025-04-15",
    "subjectName": "Law",
    "scholarshipDescription": "This scholarship is for exceptional undergraduate law students.",
    "stipend": "15000 annually",
    "postDate": "2025-02-10",
    "serviceCharge": "120",
    "applicationFees": "40"
  },
  {
    "universityName": "University of Cambridge",
    "universityImage": "https://i.ibb.co.com/vcSfWgr/477px-Cambridge-University-Crest-flat.png",
    "scholarshipCategory": "Postgraduate",
    "universityLocation": { "country": "UK", "city": "Cambridge" },
    "applicationDeadline": "2025-05-01",
    "subjectName": "Philosophy",
    "scholarshipDescription": "For postgraduate students specializing in Philosophy.",
    "stipend": "17000 annually",
    "postDate": "2025-02-12",
    "serviceCharge": "130",
    "applicationFees": "50"
  },
  {
    "universityName": "Yale University",
    "universityImage": "https://i.ibb.co.com/JcHsh97/Yale-University-Shield-1-svg.png",
    "scholarshipCategory": "Creative Arts",
    "universityLocation": { "country": "USA", "city": "New Haven" },
    "applicationDeadline": "2025-03-10",
    "subjectName": "Fine Arts",
    "scholarshipDescription": "A scholarship for students excelling in fine arts and creativity.",
    "stipend": "12000 annually",
    "postDate": "2025-02-15",
    "serviceCharge": "90",
    "applicationFees": "40"
  },
  {
    "universityName": "Columbia University",
    "universityImage": "https://i.ibb.co.com/0Dx4Yk5/Columbia-coat-of-arms-no-crest-svg.png",
    "scholarshipCategory": "Leadership Development",
    "universityLocation": { "country": "USA", "city": "New York" },
    "applicationDeadline": "2025-06-15",
    "subjectName": "Public Policy",
    "scholarshipDescription": "For students interested in leadership roles in public policy.",
    "stipend": "20000 annually",
    "postDate": "2025-02-18",
    "serviceCharge": "140",
    "applicationFees": "65"
  },
  {
    "universityName": "University of California, Berkeley",
    "universityImage": "https://i.ibb.co.com/vXkHcS0/Seal-of-University-of-California-Berkeley-svg.png",
    "scholarshipCategory": "Environmental Impact",
    "universityLocation": { "country": "USA", "city": "Berkeley" },
    "applicationDeadline": "2025-07-01",
    "subjectName": "Environmental Studies",
    "scholarshipDescription": "For students committed to addressing environmental challenges.",
    "stipend": "14000 annually",
    "postDate": "2025-02-20",
    "serviceCharge": "110",
    "applicationFees": "55"
  },
  {
    "universityName": "California Institute of Technology (Caltech)",
    "universityImage": "https://i.ibb.co.com/P6wF877/Seal-of-the-California-Institute-of-Technology-svg.png",
    "scholarshipCategory": "STEM",
    "universityLocation": { "country": "USA", "city": "Pasadena" },
    "applicationDeadline": "2025-06-20",
    "subjectName": "Physics",
    "scholarshipDescription": "For students excelling in theoretical or applied physics.",
    "stipend": "18000 annually",
    "postDate": "2025-02-25",
    "serviceCharge": "160",
    "applicationFees": "80"
  },
  {
    "universityName": "University of Chicago",
    "universityImage": "https://i.ibb.co.com/FmPtW7H/University-of-Chicago-shield-svg.png",
    "scholarshipCategory": "PhD",
    "universityLocation": { "country": "USA", "city": "Chicago" },
    "applicationDeadline": "2025-08-01",
    "subjectName": "Mathematics",
    "scholarshipDescription": "For PhD students specializing in advanced mathematics.",
    "stipend": "22000 annually",
    "postDate": "2025-03-01",
    "serviceCharge": "180",
    "applicationFees": "85"
  },
  {
    "universityName": "University of Edinburgh",
    "universityImage": "https://i.ibb.co.com/7kLxsbb/images.png",
    "scholarshipCategory": "Global Outreach",
    "universityLocation": { "country": "Scotland", "city": "Edinburgh" },
    "applicationDeadline": "2025-09-01",
    "subjectName": "International Relations",
    "scholarshipDescription": "For students pursuing global studies and international diplomacy.",
    "stipend": "10000 annually",
    "postDate": "2025-03-05",
    "serviceCharge": "90",
    "applicationFees": "60"
  },
  {
    "universityName": "University of Hong Kong",
    "universityImage": "https://i.ibb.co.com/kM7Hh26/University-of-Hong-Kong-coat-of-arms.png",
    "scholarshipCategory": "Technology",
    "universityLocation": { "country": "Hong Kong", "city": "Hong Kong" },
    "applicationDeadline": "2025-10-01",
    "subjectName": "Artificial Intelligence",
    "scholarshipDescription": "For students innovating in the field of AI and technology.",
    "stipend": "16000 annually",
    "postDate": "2025-03-10",
    "serviceCharge": "130",
    "applicationFees": "70"
  },
  {
    "universityName": "University of Amsterdam",
    "universityImage": "https://i.ibb.co.com/2715qZs/Amsterdamuniversitylogo-svg.png",
    "scholarshipCategory": "Social Science",
    "universityLocation": { "country": "Netherlands", "city": "Amsterdam" },
    "applicationDeadline": "2025-11-01",
    "subjectName": "Sociology",
    "scholarshipDescription": "For students studying social science and sociology.",
    "stipend": "13000 annually",
    "postDate": "2025-03-15",
    "serviceCharge": "100",
    "applicationFees": "65"
  }
]
